p2p_payme/__init__.py
p2p_payme/cli.py
p2p_payme/api/__init__.py
p2p_payme/api/base.py
p2p_payme/auth/__init__.py
p2p_payme/auth/api.py
p2p_payme/auth/scheme.py
p2p_payme/client/__init__.py
p2p_payme/client/manager.py
p2p_payme/client/operations.py
p2p_payme/client/scheme.py
p2p_payme/config/__init__.py
p2p_payme/config/constants.py
p2p_payme-0.1.4.dist-info/METADATA
p2p_payme-0.1.4.dist-info/WHEEL
p2p_payme-0.1.4.dist-info/entry_points.txt
p2p_payme-0.1.4.dist-info/top_level.txt
p2p_payme-0.1.4.dist-info/RECORD
