Metadata-Version: 2.1
Name: p2p-payme
Version: 0.1.4
Summary: P2P automation
Home-page: https://github.com/Abdulvoris101/p2p-payme
Author: Abdulvoris Erkinov
Author-email: erkinovabdulvoris101@gmail.com
License: UNKNOWN
Keywords: python payme p2p automation
Platform: UNKNOWN
Requires-Dist: pydantic-collections (==0.5.0)
Requires-Dist: pydantic (<2.0.0,>=1.7.4)
Requires-Dist: python-dateutil (==2.8.2)
Requires-Dist: python-dotenv (==1.0.0)
Requires-Dist: requests (==2.31.0)
Requires-Dist: typing-extensions (==4.7.1)
Requires-Dist: urllib3 (==2.0.4)
